bungocrypt/Crypt.py
bungocrypt/Key.py
bungocrypt-1.0.3.dist-info/METADATA
bungocrypt-1.0.3.dist-info/WHEEL
bungocrypt-1.0.3.dist-info/top_level.txt
bungocrypt-1.0.3.dist-info/RECORD
